epub_simplifier/__init__.py
epub_simplifier/simplifier.py
epub_simplifier-0.0.5.dist-info/LICENSE
epub_simplifier-0.0.5.dist-info/METADATA
epub_simplifier-0.0.5.dist-info/WHEEL
epub_simplifier-0.0.5.dist-info/entry_points.txt
epub_simplifier-0.0.5.dist-info/top_level.txt
epub_simplifier-0.0.5.dist-info/RECORD
