Metadata-Version: 2.1
Name: epub-simplifier
Version: 0.0.5
Summary: A command-line tool to simplify language in EPUB books
Author-email: Anatolii Bubenkov <bubenkoff@gmail.com>
Project-URL: Repository, https://github.com/bubenkoff/epub-simplifier.git
Project-URL: Issues, https://github.com/bubenkoff/epub-simplifier/issues
Keywords: epub,language,simplification,tool
Classifier: Development Status :: 5 - Production/Stable
Classifier: Programming Language :: Python :: 3
Classifier: License :: OSI Approved :: MIT License
Classifier: Operating System :: OS Independent
Requires-Python: >=3.8
License-File: LICENSE
Requires-Dist: EbookLib >=0.17.1
Requires-Dist: openai >=0.2.6
Requires-Dist: progress >=1.6
Requires-Dist: markdownify >=0.11.6
Requires-Dist: markdown2 >=2.4.13
Requires-Dist: tenacity >=8.2.3
Requires-Dist: tiktoken >=0.1.1
Provides-Extra: dev
Requires-Dist: black ; extra == 'dev'
Requires-Dist: flake8-pyproject ; extra == 'dev'
Requires-Dist: flake8 ; extra == 'dev'
Requires-Dist: pytest ; extra == 'dev'
Requires-Dist: pytest-asyncio ; extra == 'dev'
Requires-Dist: pytest-mock ; extra == 'dev'
Requires-Dist: pytest-cov ; extra == 'dev'
Requires-Dist: build ; extra == 'dev'
Requires-Dist: twine ; extra == 'dev'
